{
 "I-It's freezing...": "C-C'est glacial...",
 "Could you bring me a blanket or something?": "Tu pourrais m'apporter une couverture ou quelque chose ?",
 "Oh, it looks like you finally made it?": "Oh, tu y es finalement arrivé(e) ?",
 "I guess I'll try to stop you even though I know I pretty much have no chance.": "Je vais quand même essayer de t'arrêter même si je sais que je n'ai pratiquement aucune chance.",
 "That's generally what I expected so no big deal.": "C'est à peu près ce que j'attendais, donc pas de souci.",
 "Activate the Neutral Crystal?": "Activer le Cristal Neutre ?",
 "All of the Neutral Crystals scattered in the mountain have activated!": "Tous les Cristaux Neutres dispersés dans la montagne se sont activés !",
 "Neutral energy filled the mountain to the brim!": "L'énergie neutre a rempli la montagne jusqu'au bord !",
 "This crystal is devoid of energy.": "Ce cristal est dépourvu d'énergie.",
 "\\PN found a Zygarde Cell!": "\\PN a trouvé une Cellule de Zygarde !",
 "\\PN put the Zygarde Cell in the Gather Cube!": "\\PN place la Cellule de Zygarde dans le Cube Collecteur !",
 "Your party has been healed!": "Votre équipe a été soignée !",
 "Activate the Valor Crystal?": "Activer le Cristal de Valeur ?",
 "All of the Valor Crystals scattered in the mountain have activated!": "Tous les Cristaux de Valeur dispersés dans la montagne se sont activés !",
 "Valor energy filled the mountain to the brim!": "L'énergie de valeur a rempli la montagne jusqu'au bord !",
 "WARNING!": "AVERTISSEMENT !",
 "Trial participants should proceed with caution.": "Les participants à l'épreuve doivent avancer avec prudence.",
 "GRUNT: I'm not here to bother you. I would rather chat.": "GRUNT: Je ne suis pas là pour t'embêter. Je préférerais discuter.",
 "Did you know that the people of Terajuma worship this mountain?": "Tu savais que les habitants de Terajuma vénèrent cette montagne ?",
 "They believe it to be a manifestation of a certain God.": "Ils croient qu'elle est la manifestation d'un certain Dieu.",
 "It's even said that, at some point, people used to reside within the mountain itself.": "On dit même qu'à une époque, des gens habitaient à l'intérieur de la montagne.",
 "I wonder what happened that drove everyone out?": "Je me demande ce qui s'est passé pour que tout le monde parte ?",
 "SCIENTIST: If Geara was correct on his analysis, this should be a Source Crystal.": "SCIENTIST: Si l'analyse de Geara était correcte, ce devrait être un Cristal Source.",
 "All you would have to do is sprinkle some of this powder on top of the crystal, and the mountain should change in some way.": "Il suffirait de saupoudrer un peu de cette poudre sur le cristal, et la montagne devrait changer d'une certaine façon.",
 "We wouldn't have to forcibly change the mountain anymore!": "On n'aurait plus à modifier la montagne de force !",
 "SCIENTIST: W-Wah?! Aren't you \\PN? We were warned about you!": "SCIENTIST: Q-Quoi ?! Tu n'es pas \\PN ? On nous a prévenus de ta venue !",
 "If you used these crystals to reach the top of the mountain, I wouldn't hear the end of it from Geara!": "Si tu utilisais ces cristaux pour atteindre le sommet de la montagne, je n'entendais plus la fin de l'histoire avec Geara !",
 "Then where would I be? I won't stand for this!": "Et moi, où j'en serais ? Je ne l'accepterai pas !",
 "SCIENTIST: I didn't expect to win against you. A lowly grunt against \\PN?": "SCIENTIST: Je ne m'attendais pas à gagner contre toi. Un simple sbire contre \\PN ?",
 "The power hierarchy doesn't allow for such a circumstance to exist.": "La hiérarchie du pouvoir n'autorise pas une telle circonstance à exister.",
 "Nevertheless, I'm going to report this immediately!": "Néanmoins, je vais le signaler immédiatement !",
 "...": "...",
 "Yes": "Oui",
 "No": "Non",
 "This is not a peaceful floor! Wild Pokémon may attack!": "Cet étage n'est pas paisible ! Des Pokémon sauvages peuvent attaquer !",
 "\\v[2] remembers when it found you here. It was quite scared, but no longer.": "\\v[2] se souvient du moment où il t'a trouvé(e) ici. Il avait très peur, mais plus maintenant.",
 "\\v[2] feels proud to have been your Pokémon!": "\\v[2] est fier d'avoir été ton Pokémon !",
 "\\v[2]'s memories make it feel calm... It learned a new Fighting technique!": "Les souvenirs de \\v[2] l'apaisent... Il a appris une nouvelle technique de type Combat !",
 "\\v[2] resonated with the orb!": "\\v[2] est entré en résonance avec l'orbe !",
 "\\v[2] learned a new technique!": "\\v[2] a appris une nouvelle technique !"
}