{
  "\\PN found a Zygarde Cell!": "\\PN a trouvé une Cellule de Zygarde !",
  "\\PN put the Zygarde Cell in the Gather Cube!": "\\PN place la Cellule de Zygarde dans le Cube Collecteur !",
  "...": "...",
  "Yes": "Oui",
  "No": "Non",
  "Mesprit was dragged out of hiding!": "Créfollet a été forcé de sortir de sa cachette !",
  "VENAM: Did you see all that?": "VENAM: T'as vu tout ça ?",
  "AMBER: No, I was pissing myself. Of course I saw it!": "AMBER: Non, je faisais dans mon froc. Bien sûr que j'ai vu !",
  "\\PN battled that Pokémon and then picked up some red gemstone.": "\\PN a combattu ce Pokémon et a ramassé une sorte de gemme rouge.",
  "But what's so bad about that?": "Mais qu'est-ce qu'il y a de mal à ça ?",
  "VENAM: The way \\PN battled was so... Brutal. Heartless.": "VENAM: La façon dont \\PN a combattu était tellement...Brutale. Sans coeur.",
  "I've never seen them battle like that before.": "Je ne l'avais jamais vu combattre comme ça avant.",
  "AMBER: So, what then? What do we do with this information.": "AMBER: Alors, quoi ? Qu'est-ce qu'on fait de cette info ?",
  "VENAM: Compile it and send it to Erin.": "VENAM: On rassemble tout et on l'envoie à Erin.",
  "And then once that's done, we'll confront \\PN about it.": "Et une fois que c'est fait, on ira confronter \\PN à ce sujet.",
  "But for now I can surely say that... \\PN has changed.": "Mais pour l'instant, je peux dire avec certitude que... \\PN a changé.",
  "And we should watch ourselves around them.": "Et on devrait se méfier quand on est près de lui.",
  "MESPRIT: Mesprio!": "MESPRIT: Mesprio !",
  "MESPRIT: Mesprio....": "MESPRIT: Mesprio....",
  "Mesprit looks extremely angry with you for some reason...": "Créfollet a l'air extrêmement en colère contre toi, pour une raison ou une autre...",
  "It won't listen to you!": "Il ne veut pas t'écouter !",
  "Mesprit seems to be looking at your bag...": "Créfollet semble regarder ton sac...",
  "Give Mesprit a Gourmet Treat?": "Donner une Friandise Gourmet à Créfollet ?",
  "Mesprit's anger has been quelled...": "La colère de Créfollet s'est apaisée...",
  "Mesprit joined your party!": "Créfollet a rejoint ton équipe !"
}