{
 "\"Bladestar Notes!\"": "\"Notes Bladestar !\"",
 "\"Please do not place rocks on the conveyor belts until you are sure you can handle specimen's rage.": "\"Merci de ne pas placer de rochers sur les tapis roulants avant d'être sûr(e) de pouvoir gérer la rage du spécimen.",
 "Thank you!\"": "Merci !\"",
 "It's an ominous looking machine. It looks like something could fit in the middle of it.": "C'est une machine à l'air sinistre. On dirait que quelque chose pourrait s'emboîter en son centre.",
 "ANABEL: This is weird... A laptop was left behind...": "ANABEL: C'est bizarre...Un ordinateur portable a été laissé ici...",
 "The laptop itself isn't the weird part, though. This thing was wiped only recently.": "L'ordinateur portable en lui-même n'est pas la partie bizarre.Cette chose a été effacée récemment seulement.",
 "That's a bit of awkward timing on our part...": "C'est un peu mauvais timing de notre côté...",
 "There's nothing in here besides this laptop, and the conveyor belt.": "Il n'y a rien ici hormis cet ordinateur portable et le tapis roulant.",
 "Which seems to still be functioning, and also happens to lead into the room with the locked door.": "Qui semble encore fonctionner, et mène également dans la salle avec la porte verrouillée.",
 "ANABEL: ...Hear me out, \\PN. We should ride the conveyor belt into the next room.": "ANABEL: ...Écoute-moi, \\PN.On devrait prendre le tapis roulant jusqu'à la pièce suivante.",
 "I promised Looker we'd be careful, but I fear nothing will get done at this rate.": "J'ai promis à Looker qu'on ferait attention, mais je crains que rien n'avance à ce rythme.",
 "I'll go first...": "Je passerai en premier...",
 "ANABEL: ...Okay, here goes.": "ANABEL: ...Très bien, on y va.",
 "ANABEL: ...": "ANABEL: ...",
 "I... I chickened out.": "J'ai...J'ai eu la frousse.",
 "There's something in that room... I don't know what it is.": "Il y a quelque chose dans cette pièce...Je ne sais pas ce que c'est.",
 "Whatever it is... I've changed my mind. I think it would be unwise for us to go in there without Looker.": "Quoi que ce soit...J'ai changé d'avis.Je pense qu'il serait imprudent d'entrer là-dedans sans Looker.",
 "We've hit another wall. Let's head back for now.": "On a encore hit un mur.Retournons en arrière pour l'instant.",
 "ANABEL: So... How are things going? Will you be able to do anything?": "ANABEL: Alors...Comment ça avance ?Vous allez pouvoir faire quelque chose ?",
 "ERICK: It's not looking good... It looks like everything was completely wiped.": "ERICK: C'est pas brillant...On dirait que tout a été complètement effacé.",
 "But if I can recreate the system that was used I can probably get the door to open that way.": "Mais si je peux recréer le système qui était utilisé, je pourrai probablement faire ouvrir la porte comme ça.",
 "ANABEL: How long will that take?": "ANABEL: Combien de temps ça va prendre ?",
 "ERICK: If I'm only recreating the system to open up the door, it shouldn't take too long.": "ERICK: Si je recrée juste le système pour ouvrir la porte, ça ne devrait pas prendre trop longtemps.",
 "You guys should wait by the door. I've got everything under control here.": "Vous devriez attendre près de la porte.J'ai tout sous contrôle ici.",
 "LOOKER: Alright, we're counting on you Erick.": "LOOKER: D'accord, on compte sur toi Erick.",
 "ANABEL: Is... Is that the Rift being that our radars picked up?": "ANABEL: Est-ce... Est-ce l'être de la Faille que nos radars ont détecté ?",
 "LOOKER: I must say... It's much smaller than I anticipated.": "LOOKER: Je dois dire... Il est bien plus petit que ce à quoi je m'attendais.",
 "ANABEL: Considering the usual threat level of these beings...": "ANABEL: Vu le niveau de menace habituel de ces êtres...",
 "I don't think we'll be able to just take it with us just like that.": "Je ne pense pas qu'on pourra juste l'emmener avec nous comme ça.",
 "We're going to have to weaken it significantly.": "On va devoir l'affaiblir considérablement.",
 "LOOKER: \\PN, this is where you come in.": "LOOKER: \\PN, c'est là que tu interviens.",
 "Like Anabel said before- You have the most experience fighting these things.": "Comme Anabel l'a dit avant - tu as le plus d'expérience pour combattre ces créatures.",
 "So we'd greatly appreciate it if you would do the same for this one.": "Nous apprécierions donc beaucoup que tu fasses de même pour celui-ci.",
 "ANABEL: Good luck, \\PN.": "ANABEL: Bonne chance, \\PN.",
 "???: Faaaaa!": "???: Faaaaa !",
 "LOOKER: Please, take your time. I don't think this one will attack us... for now.": "LOOKER: S'il te plaît, prends ton temps. Je ne pense pas que celui-ci nous attaquera... pour l'instant.",
 "ANABEL: Uh, I think that'll be enough for now.": "ANABEL: Euh, je pense que ça suffira pour l'instant.",
 "LOOKER: Yeah, I can't really say this thing looks happy with us.": "LOOKER: Ouais, on peut pas vraiment dire que cette créature a l'air contente de nous.",
 "ANABEL: Can you really blame the poor thing? We just entered its home uninvited and attacked it.": "ANABEL: Peut-on vraiment le lui reprocher ?Nous venons d'entrer chez lui sans invitation et de l'attaquer.",
 "However, I didn't expect it to change form mid-way through battle...": "Cependant, je ne m'attendais pas à ce qu'il change de forme en plein combat...",
 "We should grab it and call HQ. I'm sure they'll be interested in this.": "On devrait le récupérer et appeler le QG.Je suis sûre qu'ils seront intéressés.",
 "LOOKER: Great job, \\PN. You did marvelously.": "LOOKER: Excellent travail, \\PN.Tu t'en es sorti(e) à merveille.",
 "ANABEL: Let's leave this place once and for all. We got what we came for.": "ANABEL: Quittons cet endroit une bonne fois pour toutes.Nous avons ce pour quoi nous sommes venus.",
 "LOOKER: Agreed. Wearing a trench coat in this heat will be the death of me.": "LOOKER: D'accord.Porter un imperméable par cette chaleur finira par me tuer.",
 "Activate the panel?": "Activer le panneau ?",
 "A door opens somewhere nearby...": "Une porte s'ouvre quelque part à proximité...",
 "Seems to be a journal written by Flora.": "On dirait un journal écrit par Flora.",
 "Read it?": "Le lire ?",
 "\"FLORA: All right, well, I'm going to be writing down my progress as we go through with this experiment.": "\"FLORA: Bien, je vais noter mes progrès au fur et à mesure de cette expérience.",
 "I had to go through a lot of hoops to obtain Rift Matter from the Xen HQ in the Badlands.": "J'ai dû sauter par-dessus beaucoup d'obstacles pour obtenir de la Matière de Faille au QG de Xen dans les Terres Désolées.",
 "I gotta say, for such an incompetent bunch of weirdos, they sure can defend their base.": "Je dois dire que pour un groupe aussi incompétent d'individus bizarres, ils savent bien défendre leur base.",
 "There were turrets everywhere, magma moats surrounding the front entrance...": "Il y avait des tourelles partout, des douves de magma entourant l'entrée principale...",
 "It was pretty impressive, but it was nothing I couldn't handle.": "C'était assez impressionnant, mais rien que je ne puisse gérer.",
 "Anyway, we're going to use the Rift Matter on my Ferrothorn in a few days.": "Quoi qu'il en soit, nous allons utiliser la Matière de Faille sur mon Noacier dans quelques jours.",
 "I don't know what the exact effects will be, but I presume Ferrothorn will get a huge increase in power.": "Je ne sais pas quels seront les effets exacts, mais je présume que Noacier obtiendra une énorme augmentation de puissance.",
 "That's exactly what we need if we're going to overthrow Cassandra.\"": "C'est exactement ce dont nous avons besoin si nous voulons renverser Cassandra.\"",
 "Read more?": "Lire la suite ?",
 "\"FLORA: So... We went ahead and applied Rift Matter to Ferrothorn and it went through immediate physical and psychological changes.": "\"FLORA: Alors... Nous avons appliqué la Matière de Faille sur Noacier et il a subi des changements physiques et psychologiques immédiats.",
 "Could this thing even be called Ferrothorn at this point? None can say...": "Peut-on encore appeler cette créature Noacier à ce stade ? Nul ne peut le dire...",
 "Truth be told, I feel really bad for doing this to the poor guy, but we all have to make sacrifices.": "À vrai dire, je me sens vraiment mal de lui avoir fait ça, mais nous devons tous faire des sacrifices.",
 "After it changed, it refused to listen to a word I said to it. It became 100% truant.": "Après sa transformation, il a refusé d'écouter un seul mot de ce que je lui disais. Il est devenu(e) 100 % flemmard.",
 "This was troublesome because I'm gonna, you know, need it to listen to me if we're going to get anything done?": "C'était gênant parce que j'allais, tu vois, avoir besoin qu'il m'écoute si on voulait accomplir quoi que ce soit.",
 "What's interesting to note is that it doesn't attack unless you attack it first. Does it just not care?": "Ce qui est intéressant à noter c'est qu'il n'attaque que si on l'attaque en premier. Il s'en fiche vraiment ?",
 "Regardless, this isn't going the way I had hoped and I'm getting increasingly more frustrated.": "Quoi qu'il en soit, ça ne se passe pas comme je l'espérais et je deviens de plus en plus frustrée.",
 "Perhaps the new recruit will be able to help me figure this out. After all, he's a scientist.\"": "Peut-être que la nouvelle recrue pourra m'aider à comprendre ça. Après tout, c'est un scientifique.\"",
 "\"FLORA: The new recruit and I figured out a new way to control this being.": "\"FLORA: La nouvelle recrue et moi avons trouvé un nouveau moyen de contrôler cet être.",
 "If there's a way for me to grasp its vines without burning myself, I could probably use Ferrothorn as its own weapon.": "S'il y a un moyen de saisir ses lianes sans me brûler, je pourrais probablement utiliser Noacier comme sa propre arme.",
 "I can swing it around like a yo-yo. The best part about that is that it has layers on its body that can move.": "Je peux le faire tournoyer comme un yo-yo. Le mieux là-dedans, c'est qu'il a des couches sur son corps qui peuvent bouger.",
 "That in mind, I taught it how to quickly dodge and evade when it gets attacked.": "Avec ça en tête, je lui ai appris à esquiver et éviter rapidement quand il se fait attaquer.",
 "After we trained for a few weeks, I decided I wanted to test its power myself.": "Après quelques semaines d'entraînement, j'ai décidé de tester sa puissance moi-même.",
 "We had three battles in total. The first battle I barely came out on top.": "Nous avons eu trois combats en tout. Au premier combat, je m'en suis à peine sortie gagnante.",
 "The second battle resulted in a draw. This pleased me for the most part.": "Le deuxième combat s'est terminé par un match nul. Cela m'a satisfaite en grande partie.",
 "As for the third battle... This is where things became interesting. It changed its strategy to precisely counter mine.": "Quant au troisième combat... C'est là que les choses sont devenues intéressantes. Il a changé de stratégie pour contrer précisément la mienne.",
 "Instead of keeping its natural form, it let go of the walls around it and started drifting around the room like a wheel.": "Au lieu de garder sa forme naturelle, il a lâché les murs autour de lui et a commencé à dériver dans la pièce comme une roue.",
 "The speed this thing was going was absolutely incredible. I've never seen anything like it.": "La vitesse à laquelle cette chose se déplaçait était absolument incroyable. Je n'avais jamais rien vu de tel.",
 "Unfortunately, its movements were predictable. I was able to defeat it quite easily.": "Malheureusement, ses mouvements étaient prévisibles. J'ai réussi à le vaincre assez facilement.",
 "We're going to close this experiment for now, but I'll return to this being one day.\"": "Nous allons clore cette expérience pour l'instant, mais je reviendrai vers cet être un jour.\"",
 "Read More?": "Lire la suite ?",
 "In my time wandering around the Scholar Library I came across a very interesting book.": "En me promenant dans la Bibliothèque des Érudits, je suis tombée sur un livre très intéressant.",
 "It was solely dedicated to the topic of Team Meteor from the Reborn Region.": "Il était entièrement consacré au sujet de la Team Meteor de la Région Reborn.",
 "I have heard of their efforts in the Reborn Region many years ago, but I did not know the details of their efforts.": "J'avais entendu parler de leurs efforts dans la Région Reborn il y a de nombreuses années, mais je ne connaissais pas les détails de leurs actions.",
 "They called this machine the PULSE machine.": "Ils appelaient cette machine la machine PULSE.",
 "I was heavily intrigued until I read about one small detail- The effect it had on its host.": "J'étais très intriguée jusqu'à ce que je lise un petit détail - l'effet qu'elle avait sur son hôte.",
 "So instead of rebuilding an exact copy of the PULSE machines Team Meteor created, I built my own version.": "Alors au lieu de reconstruire une copie exacte des machines PULSE créées par la Team Meteor, j'ai construit ma propre version.",
 "This is exactly what I needed in order to go on with my plans.": "C'est exactement ce dont j'avais besoin pour poursuivre mes plans.",
 "As a result, the purpose of this lab is now complete.": "En conséquence, l'objectif de ce laboratoire est maintenant atteint.",
 "We'll be heading out in a few days and this whole place should be blocked off to the public.": "Nous partirons dans quelques jours et tout cet endroit devrait être interdit au public.",
 "When the time has come to release my dear Ferrothorn, I shall return.": "Quand le moment sera venu de libérer mon cher Noacier, je reviendrai.",
 "Until then... I have other things to deal with. Goodbye\"": "D'ici là... J'ai d'autres choses à régler. Au revoir\"",
 "I'm ready!": "Je suis prêt(e) !",
 "On second thought...": "En fait...",
 "Yes": "Oui",
 "No": "Non",
 "ANABEL: So, you've returned? Are you ready to face the Rift Pokémon?": "ANABEL: Alors, tu es de retour ? Prêt(e) à affronter le Pokémon de la Faille ?",
 "Looking at it, I thought it was just some standard Rift Pokémon.": "En le voyant, je pensais que c'était simplement un Pokémon de la Faille standard.",
 "\"FLORA: Instead of going with the Rift Matter, I decided to do some research on a Pokémon enhancement.": "\"FLORA: Au lieu de m'orienter vers la Matière de Faille, j'ai décidé de mener des recherches sur une amélioration des Pokémon. ",
 "They had access to a strange machine that could amplify the power of Pokémon to an incredible amount.": "Ils avaient accès à une étrange machine capable d'amplifier considérablement la puissance des Pokémon. ",
 "The machine is a parasite. It takes a huge toll on the Pokémon it amplifies.": "La machine est un parasite. Elle épuise énormément les Pokémon qu'elle amplifie. ",
 "Despite doing experiments on my Ferrothorn, I'm not about having Pokémon suffer all the time.": "Même si je mène des expériences sur mon Noacier, je ne suis pas du genre à faire souffrir les Pokémon en permanence. ",
 "A machine that is able to be both beneficial to the Pokémon and to the user of the PULSE machine.": "Une machine capable d'être bénéfique à la fois au Pokémon et à l'utilisateur de la machine PULSE. "
}