{
 "\"The shadows that shade the earth shall be known in the end.": "\"The shadows that shade the earth shall be known in the end.",
 "\"The one of raw evil, the one of obsession, the one of betrayal, and the one of greed.": "\"The one of raw evil, the one of obsession, the one of betrayal, and the one of greed.",
 "These four shall see the world be lost forever.\"": "These four shall see the world be lost forever.\" ",
 "You can't read any of this...": "You can't read any of this...",
 "GUARD: Don't do anything stupid. Just do your job and leave.": "GUARD: Don't do anything stupid. Just do your job and leave.",
 "VALARIE: This thing is clearly not doing well.": "VALARIE: This thing is clearly not doing well.",
 "Locked!": "Locked!",
 "Locked.": "Locked.",
 "Locked...": "Locked...",
 "SAKI: Oh mah gawww, finally.": "SAKI: Oh mah gawww, finally. ",
 "That riddle I gave you, if you can even call it that, was made in 5 minutes!": "That riddle I gave you, if you can even call it that, was made in 5 minutes!",
 "But you solved it! You're a genius!": "But you solved it! You're a genius!",
 "SAKI: U rite, tho. Valarie told me to make it on short notice. I didn't have time to think!": "SAKI: U rite, tho. Valarie told me to make it on short notice. I didn't have time to think!",
 "SAKI: Tee hee, I knew it was pretty good. Had you fooled! Aha!": "SAKI: Tee hee, I knew it was pretty good. Had you fooled! Aha!",
 "Even if it was bad, thanks for telling me it was good. 'Preciate it.": "Even if it was bad, thanks for telling me it was good. 'Preciate it.",
 "C'mon, everyone's waiting. Let's go!": "C'mon, everyone's waiting. Let's go!",
 "GUARD: Miss Blakeory, stop running around this instant!": "GUARD: Miss Blakeory, stop running around this instant!",
 "SAKI: Awww, what's wrong, Mr. Guard? Am I causing a scene?": "SAKI: Awww, what's wrong, Mr. Guard? Am I causing a scene?",
 "Sorry, but I can do whatever I want! I don't care what you say!": "Sorry, but I can do whatever I want!  I don't care what you say!",
 "GUARD: Stop this, or you'll regret it!": "GUARD: Stop this, or you'll regret it!",
 "SAKI: Tell that to my boney Sinnohian ass!": "SAKI: Tell that to my boney Sinnohian ass!",
 "SAKI: WHOMP WHOMP WHOMP WHOMP WHOMP WHOMP WHOMP.": "SAKI: WHOMP WHOMP WHOMP WHOMP WHOMP WHOMP WHOMP.",
 "BRAIXEN: Oh, this isn't good...": "BRAIXEN: Oh, this isn't good...",
 "BRAIXEN: Saki's good at being annoying and bringing attention to herself, much to our advantage.": "BRAIXEN: Saki's good at being annoying and bringing attention to herself, much to our advantage.",
 "ADAM: You think you can get anything from this?": "ADAM: You think you can get anything from this?",
 "BRAIXEN: Saki used to tinker with programming, machines, and all that.": "BRAIXEN: Saki used to tinker with programming, machines, and all that. ",
 "Fortunately for us, I had to be there to watch her do all that boring stuff, so I picked up a thing or two.": "Fortunately for us, I had to be there to watch her do all that boring stuff, so I picked up a thing or two.",
 "From what I can tell, these Sigils are being powered and controlled from elsewhere.": "From what I can tell, these Sigils are being powered and controlled from elsewhere.",
 "These panels that appear can only change the local settings.": "These panels that appear can only change the local settings.",
 "VALARIE: Local settings?": "VALARIE: Local settings?",
 "BRAIXEN: Yeah, like, the intensity of the signals, how aggressive the controlled Pokémon should be.": "BRAIXEN: Yeah, like, the intensity of the signals, how aggressive the controlled Pokémon should be.",
 "All of that dark stuff. Really dark.": "All of that dark stuff. Really dark.",
 "ADAM: So what you're saying is that we're not able to do anything here.": "ADAM: So what you're saying is that we're not able to do anything here.",
 "BRAIXEN: Maybe if we can change the intensity to the lowest setting, some of us can break free.": "BRAIXEN: Maybe if we can change the intensity to the lowest setting, some of us can break free.",
 "But that can be changed at any time. So it's unreliable. How annoying!": "But that can be changed at any time. So it's unreliable. How annoying!",
 "VALARIE: Hm... Maybe we should stop messing with this for now.": "VALARIE: Hm... Maybe we should stop messing with this for now.",
 "We don't want to be caught, and Braixen needs to get back to the house.": "We don't want to be caught, and Braixen needs to get back to the house.",
 "BRAIXEN: Yeah... I'll get going. It was nice meeting you, \\PN.": "BRAIXEN: Yeah... I'll get going. It was nice meeting you, \\PN.",
 "VALARIE: As for us, we should get to the Dining Hall. We can discuss more there.": "VALARIE: As for us, we should get to the Dining Hall. We can discuss more there.",
 "ADAM: Alright, let's go.": "ADAM: Alright, let's go.",
 "ADAM: ...": "ADAM: ...",
 "It may be too risky to go down these stairs...": "It may be too risky to go down these stairs...",
 "No need to go further!": "No need to go further!",
 "SAKI: Wow, it's already all smokey and harsh out here...": "SAKI: Wow, it's already all smokey and harsh out here...",
 "VALARIE: Emma and Adam must've noticed that the Sigils have finally died down.": "VALARIE: Emma and Adam must've noticed that the Sigils have finally died down.",
 "Word of this must've spread, and well... This is the result.": "Word of this must've spread, and well... This is the result.",
 "SAKI: With Braixen leading all of the survivors of the S.S. Oceana through the library's hidden passage, everything's falling into place!": "SAKI: With Braixen leading all of the survivors of the S.S. Oceana through the library's hidden passage, everything's falling into place!",
 "VALARIE: We don't know what's happening at the castle yet, though.": "VALARIE: We don't know what's happening at the castle yet, though.",
 "For all we know things might be going down poorly. We have to regroup with Emma and Adam.": "For all we know things might be going down poorly. We have to regroup with Emma and Adam.",
 "Then we'll get everyone boarded on the ship. We don't have much time!": "Then we'll get everyone boarded on the ship. We don't have much time!",
 "SAKI: Roger that! Let's go!": "SAKI: Roger that! Let's go!",
 "MOM: \\PN. Let's fight together this time. With our strength, we're unstoppable!": "MOM: \\PN. Let's fight together this time. With our strength, we're unstoppable!",
 "Let's show them the power we hold!": "Let's show them the power we hold!",
 "MOM: Are you ready to go?": "MOM: Are you ready to go?",
 "MOM: Come, let's leave this wretched prison!": "MOM: Come, let's leave this wretched prison!",
 "GUARD: Wh-What? Where did you come from?!": "GUARD: Wh-What? Where did you come from?!",
 "MOM: I don't think you need to worry about that.": "MOM: I don't think you need to worry about that.",
 "GUARD: E-Enough, just surrender!": "GUARD: E-Enough, just surrender!",
 "MOM: I don't think we will. Just stand aside.": "MOM: I don't think we will. Just stand aside.",
 "GUARD: Neved... Sir...": "GUARD: Neved... Sir...",
 "GUARD: What happened to the Sigils? They just lost power all of a sudden?!": "GUARD: What happened to the Sigils? They just lost power all of a sudden?!",
 "MOM: We've cut the power so now you all are left wide open!": "MOM: We've cut the power so now you all are left wide open!",
 "GUARD: This is so, so, so, so, so, so bad. I don't even know what to do right now.": "GUARD: This is so, so, so, so, so, so bad. I don't even know what to do right now.",
 "MOM: You let us leave. Do nothing.": "MOM: You let us leave. Do nothing.",
 "GUARD: ...I": "GUARD: ...I",
 "GUARD: W-Wait a minute, isn't that...? Did the S.S. Oceana prisoners escape their cells?!": "GUARD: W-Wait a minute, isn't that...? Did the S.S. Oceana prisoners escape their cells?!",
 "MOM: We're free and we'll never be enslaved again!": "MOM: We're free and we'll never be enslaved again!",
 "GUARD: I've never been much of a battler, that's fine.": "GUARD: I've never been much of a battler, that's fine.",
 "But Neved's been battling for his entire... well, life! You don't have the experience to beat him!": "But Neved's been battling for his entire... well, life! You don't have the experience to beat him!",
 "MOM: We don't need experience to handle this situation. Just back off!": "MOM: We don't need experience to handle this situation. Just back off!",
 "GUARD: Neved will deal with all of you! He'll crush your spirits!": "GUARD: Neved will deal with all of you! He'll crush your spirits!",
 "GUARD: Where do you lot get the idea that you can revolt? Behave yourselves!": "GUARD: Where do you lot get the idea that you can revolt? Behave yourselves!",
 "I don't have any Pokémon, but I don't need them to whoop you!": "I don't have any Pokémon, but I don't need them to whoop you!",
 "ARIADOS: Ari!": "ARIADOS: Ari!",
 "GUARD: Attack!": "GUARD: Attack!",
 "AMBIPOM: Amb!": "AMBIPOM: Amb!",
 "Ampibom don't scare me!": "Ampibom don't scare me!",
 "KENNETH: ...": "KENNETH: ...",
 "KETA: Why did you bring me to this insufferably cold island?": "KETA: Why did you bring me to this insufferably cold island?",
 "Sheridan is more south, I told you that.": "Sheridan is more south, I told you that.",
 "NEVED: I just wanted to bring you here so that we could talk.": "NEVED: I just wanted to bring you here so that we could talk.",
 "I, along with you, have been roped into something we would give everything to escape from.": "I, along with you, have been roped into something we would give everything to escape from.",
 "KETA: ...": "KETA: ...",
 "NEVED: Kenneth.": "NEVED: Kenneth.",
 "KETA: It's Keta. That's my Xen agent name.": "KETA: It's Keta. That's my Xen agent name.",
 "NEVED: Alright, Keta. I just wanted to let you know that you have friends here. Even if you don't want them.": "NEVED: Alright, Keta. I just wanted to let you know that you have friends here. Even if you don't want them.",
 "Being in Team Xen is a massive burden, and we're all fighting for something, but...": "Being in Team Xen is a massive burden, and we're all fighting for something, but...",
 "KETA: And just what are you fighting for?": "KETA: And just what are you fighting for?",
 "NEVED: ...My daughter, Franchesca. She's been extremely sick and-": "NEVED: ...My daughter, Franchesca. She's been extremely sick and-",
 "KETA: You realize doing this won't save her.": "KETA: You realize doing this won't save her.",
 "NEVED: H-Huh?": "NEVED: H-Huh?",
 "KETA: Team Xen isn't going to save her. No matter how loyal you are.": "KETA: Team Xen isn't going to save her. No matter how loyal you are.",
 "But we continue to do so because we want that slight glimmer of hope to be true.": "But we continue to do so because we want that slight glimmer of hope to be true.",
 "We'd give everything for it. Ruin lives, end them. Cause despair.": "We'd give everything for it. Ruin lives, end them. Cause despair.",
 "Even though I know for a fact that this is all for nothing, here I am.": "Even though I know for a fact that this is all for nothing, here I am.",
 "Because I want to protect those I love, but let's face it, Neved.": "Because I want to protect those I love, but let's face it, Neved.",
 "Everyone we know will suffer because of us.": "Everyone we know will suffer because of us.",
 "You'll never save your daughter. Forget about her. She's as good as dead.": "You'll never save your daughter. Forget about her. She's as good as dead.",
 "NEVED: ...I.": "NEVED: ...I.",
 "Your words cut deep.": "Your words cut deep.",
 "After all I did was try to help you?\\| I'll make sure you feel the same pain I do.": "After all I did was try to help you?\\| I'll make sure you feel the same pain I do.",
 "I swear to it.": "I swear to it.",
 "MELIA: ...Blacksteeple Garden.": "MELIA: ...Blacksteeple Garden.",
 "It's fallen into disrepair now that they don't have <i>slaves</i> to tend to it.": "It's fallen into disrepair now that they don't have <i>slaves</i> to tend to it.",
 "As for why they were tending to it...?": "As for why they were tending to it...?",
 "It was barely a riddle.": "It was barely a riddle.",
 "I was stumped.": "I was stumped.",
 "Let's get em!": "Let's get em!",
 "One sec...": "One sec..."
}