{
 "GRUNT: So I was talking to Valarie last night.": "GRUNT: So I was talking to Valarie last night.",
 "GRUNT2: Oh yeah? What about?": "GRUNT2: Oh yeah? What about?",
 "GRUNT: I dunno, I was thinking of... Building a haberdashery.": "GRUNT: I dunno, I was thinking of... Building a haberdashery.",
 "GRUNT2: ...A what?": "GRUNT2: ...A what?",
 "GRUNT: They sell men's clothing and accessories!": "GRUNT: They sell men's clothing and accessories!",
 "GRUNT2: Uh, keep dreaming.": "GRUNT2: Uh, keep dreaming.",
 "GRUNT: I will.": "GRUNT: I will.",
 "GRUNT: What the...? Who are you?": "GRUNT: What the...? Who are you?",
 "GRUNT: Gyahh!!": "GRUNT: Gyahh!!",
 "MADAME X: ...What?": "MADAME X: ...What?",
 "MIMIKYU: Mimi...!": "MIMIKYU: Mimi...!",
 "MADAME X: ...???": "MADAME X: ...???",
 "AMBER: Oh sweet fresh air! I've missed you!": "AMBER: Oh sweet fresh air! I've missed you!",
 "KENNETH: As fresh as it can get, I suppose.": "KENNETH: As fresh as it can get, I suppose.",
 "MOSELY: Okay, we're out now. Whadda we do now?": "MOSELY: Okay, we're out now. Whadda we do now?",
 "MELIA: We need to take control of the ship, and then after that...": "MELIA: We need to take control of the ship, and then after that...",
 "Well, I guess we can discuss what after we're successful.": "Well, I guess we can discuss what after we're successful.",
 "???: Allow me to give you some input.": "???: Allow me to give you some input.",
 "MELIA: Madame X...!": "MELIA: Madame X...!",
 "MOSELY: THAT'S THE OTHER PERSON! See, Kenneth? I told you I wasn't lying!": "MOSELY: THAT'S THE OTHER PERSON! See, Kenneth? I told you I wasn't lying!",
 "AMBER: What do you want from us?": "AMBER: What do you want from us?",
 "MELIA: She's been following \\PN and I. She's dangerous!": "MELIA: She's been following \\PN and I. She's dangerous!",
 "MADAME X: Following you? I've been cleaning up your dirt, imbeciles.": "MADAME X: Following you? I've been cleaning up your dirt, imbeciles.",
 "Now, come with me.": "Now, come with me.",
 "AMBER: Not another step, power ranger! \\PN and Melia are our friends.": "AMBER: Not another step, power ranger! \\PN and Melia are our friends.",
 "Sure, Melia's girly and naive. Sure, \\PN is quiet and kinda shady...": "Sure, Melia's girly and naive. Sure, \\PN is quiet and kinda shady...",
 "But that's what makes them cool to us!": "But that's what makes them cool to us!",
 "KENNETH: Precisely. Any more steps, and we'll be forced to take action.": "KENNETH: Precisely. Any more steps, and we'll be forced to take action.",
 "MOSELY: I DARE ya to take another step! C'mon, do it!": "MOSELY: I DARE ya to take another step! C'mon, do it!",
 "MELIA: ...Everyone.\\| Thank you.": "MELIA: ...Everyone.\\| Thank you.",
 "MADAME X: Even in a time like this you have lackeys that stoop down to your sick level.": "MADAME X: Even in a time like this you have lackeys that stoop down to your sick level.",
 "This feud is meaningless. I have no intention of harming anyone here.": "This feud is meaningless. I have no intention of harming anyone here.",
 "As a matter of fact, it's quite the opposite.\\| I offer a temporary truce, and union.": "As a matter of fact, it's quite the opposite.\\| I offer a temporary truce, and union.",
 "MADAME X: I'm afraid this isn't a matter of choice, but common interest.": "MADAME X: I'm afraid this isn't a matter of choice, but common interest.",
 "You two want to return back to our time, don't you?": "You two want to return back to our time, don't you?",
 "I believe I have a way to do so.": "I believe I have a way to do so.",
 "MELIA: ...!": "MELIA: ...!",
 "MADAME X: Because we have a common interest, do we not?": "MADAME X: Because we have a common interest, do we not?",
 "Returning to our time should be, and is, our highest priority.": "Returning to our time should be, and is, our highest priority.",
 "And I believe that I have a way to do just that.": "And I believe that I have a way to do just that.",
 "MELIA: ...": "MELIA: ...",
 "\\PNUpper: ...": "\\PNUpper: ...",
 "MADAME X: Think over your answer carefully, I won't ask for it now.": "MADAME X: Think over your answer carefully, I won't ask for it now.",
 "We have another matter to take care of first.": "We have another matter to take care of first.",
 "\\c[6]Taking control of this ship.": "\\c[6]Taking control of this ship.",
 "AMBER: We were planning on doing that anyway.": "AMBER: We were planning on doing that anyway.",
 "MADAME X: Then there should be no issue here.": "MADAME X: Then there should be no issue here.",
 "Shall we, then?": "Shall we, then?",
 "AMBER: What do we do? We can't surely follow that lunatic?": "AMBER: What do we do? We can't surely follow that lunatic?",
 "MELIA: It's like she said. We have no choice.": "MELIA: It's like she said. We have no choice.",
 "Whether we follow her or not, our paths will cross inevitably.": "Whether we follow her or not, our paths will cross inevitably.",
 "Let's just keep going on our path and see what happens.": "Let's just keep going on our path and see what happens.",
 "KENNETH: Everyone, be on your guard. Be ready to fight if need be.": "KENNETH: Everyone, be on your guard. Be ready to fight if need be.",
 "\\ts[1]<ac>One day later.": "\\ts[1]<ac>One day later.",
 "???: \\ts[1]Beeeep.": "???: \\ts[1]Beeeep.",
 "MELIA: Uh, did you hear something?": "MELIA: Uh, did you hear something?",
 "MELIA: Yeah, I heard something like that! It was kind of like a-": "MELIA: Yeah, I heard something like that! It was kind of like a-",
 "MELIA: Huh, I guess I was just imagining things then.": "MELIA: Huh, I guess I was just imagining things then.",
 "MELIA: Fair enough, I guess. Still, I'm pretty sure I heard-": "MELIA: Fair enough, I guess. Still, I'm pretty sure I heard-",
 "???: Beeeeeep.": "???: Beeeeeep.",
 "MELIA: ...I definitely heard something that time.": "MELIA: ...I definitely heard something that time.",
 "???: BEEP BEEP BEEP BEEP BEEP!": "???: BEEP BEEP BEEP BEEP BEEP!",
 "MELIA: What the...\\| Oh, it's just her.": "MELIA: What the...\\| Oh, it's just her.",
 "VALARIE: If I'm gonna be stuck up here I'm gonna make sure NO ONE has fun on this ship.": "VALARIE: If I'm gonna be stuck up here I'm gonna make sure NO ONE has fun on this ship.",
 "Oh, what's that? You wanted to sleep?\\| Well get a load of this, Mary!": "Oh, what's that? You wanted to sleep?\\| Well get a load of this, Mary!",
 "BEEP! BEEP! BEEP! BEEP! BEEP! BEEP! BEEP! BEEP! BEEP! BEEP! BEEP! BEEP! BEEP! BEEP!": "BEEP! BEEP! BEEP! BEEP! BEEP! BEEP! BEEP!  BEEP! BEEP! BEEP! BEEP! BEEP! BEEP! BEEP! ",
 "MELIA: Was it really a good idea to just put her up there like that?": "MELIA: Was it really a good idea to just put her up there like that?",
 "MELIA: And we sure got one, huh? This one has an alarm and everything.": "MELIA: And we sure got one, huh? This one has an alarm and everything.",
 "The Valarie we knew was a lot quieter than this.": "The Valarie we knew was a lot quieter than this.",
 "I hope she's doing well... If she's doing... anything at all?": "I hope she's doing well... If she's doing... anything at all?",
 "MELIA: Yeah, I think I can hear her enthusiasm from here...": "MELIA: Yeah, I think I can hear her enthusiasm from here...",
 "You know what? I'm happy for her.": "You know what? I'm happy for her.",
 "Hopefully the Valarie we know is doing well right now... If she exists?": "Hopefully the Valarie we know is doing well right now... If she exists?",
 "MELIA: I guess she did lock us up... But I feel bad.": "MELIA: I guess she did lock us up... But I feel bad.",
 "Even if it's not the Valarie WE know, it's still Valarie.": "Even if it's not the Valarie WE know, it's still Valarie.",
 "If.... When we get back home, I'll take her out to lunch or something.": "If.... When we get back home, I'll take her out to lunch or something.",
 "MOSELY: Hey look at these two saps. Lookin' kinda depressed!": "MOSELY: Hey look at these two saps. Lookin' kinda depressed!",
 "MELIA: You could say that... Yeah.": "MELIA: You could say that... Yeah.",
 "AMBER: Don't worry, you won't be depressed after you see... \\| THIS.": "AMBER: Don't worry, you won't be depressed after you see... \\| THIS.",
 "AMBER: ...": "AMBER: ...",
 "MOSELY: ...": "MOSELY: ...",
 "MELIA: ...?": "MELIA: ...?",
 "\\PNUpper: ... :)": "\\PNUpper: ... :)",
 "MELIA: Where'd you get that eye patch?": "MELIA: Where'd you get that eye patch?",
 "AMBER: Thought I'd give Valarie's desk a bit of a clean up.": "AMBER: Thought I'd give Valarie's desk a bit of a clean up.",
 "Found this bad boy and slapped it right on because it makes me look hot and badass.": "Found this bad boy and slapped it right on because it makes me look hot and badass.",
 "MOSELY: Sorry to butt in, but all it does is make you look like a big stupid COW.": "MOSELY: Sorry to butt in, but all it does is make you look like a big stupid COW.",
 "I WAS THE ONE WHO FOUND THE EYE PATCH!": "I WAS THE ONE WHO FOUND THE EYE PATCH!",
 "AMBER: And I'm the one who put it on. What's your point?": "AMBER: And I'm the one who put it on. What's your point?",
 "MOSELY: Since you're gonna be wearing an eye patch, you won't mind if I deck it out of your skull, right?": "MOSELY: Since you're gonna be wearing an eye patch, you won't mind if I deck it out of your skull, right?",
 "AMBER: The adults are talking, kiddo.\\n\\| Get off the SCREEN!": "AMBER: The adults are talking, kiddo.\\n\\| Get off the SCREEN!",
 "AMBER: Anyway, I found something else while rummaging through Valarie's things.": "AMBER: Anyway, I found something else while rummaging through Valarie's things.",
 "This <icon=redkey> was just sitting there all lonely under a bunch of ketchup packets.": "This <icon=redkey> was just sitting there all lonely under a bunch of ketchup packets.",
 "Don't ask me why there were ketchup packets in there, I don't know the answer to that.": "Don't ask me why there were ketchup packets in there, I don't know the answer to that.",
 "But if you ask me, I think this key is for that huge door inside the ship.": "But if you ask me, I think this key is for that huge door inside the ship.",
 "MELIA: We should go check it out then. I was curious about that door before...": "MELIA: We should go check it out then. I was curious about that door before...",
 "AMBER: Now you're speaking my language. Let's meet up there, yeah?": "AMBER: Now you're speaking my language. Let's meet up there, yeah?",
 "MELIA: Oh, \\PN... There you are.\\| It's time.": "MELIA: Oh, \\PN... There you are.\\| It's time.",
 "AMBER: Holy shit.": "AMBER: Holy shit.",
 "VALARIE: Can I be let down from here already?!": "VALARIE: Can I be let down from here already?!",
 "I mean, it's pouring for Poochyena's sake!": "I mean, it's pouring for Poochyena's sake!",
 "AMBER: Would you just shut up? We're all getting soaked so deal with it.": "AMBER: Would you just shut up? We're all getting soaked so deal with it.",
 "VALARIE: BEEP BEEP BEEP BEEP BEEP BEEP BEEP BEEP BEEP BEEP BEEP BEEEP.": "VALARIE: BEEP BEEP BEEP BEEP BEEP BEEP BEEP BEEP BEEP BEEP BEEP BEEEP.",
 "Everyone, take a look over there!": "Everyone, take a look over there!",
 "MIMIKYU: Mimi...": "MIMIKYU: Mimi...",
 "There's no way!": "There's no way!",
 "But why?": "But why?",
 "Beep.": "Beep.",
 "Nope.": "Nope.",
 "I wasn't paying attention.": "I wasn't paying attention.",
 "We needed a new sail...": "We needed a new sail...",
 "She loves her new job.": "She loves her new job.",
 "Yes.": "Yes."
}